app/__init__.py
app/constants.py
app/funcs.py
app/main.py
app/services/__init__.py
app/services/github_service.py
app/services/phalcon_service.py
phalcon_data/__init__.py
phalcon_data/versions/__init__.py
phalcon-1.0.10.33.dist-info/METADATA
phalcon-1.0.10.33.dist-info/WHEEL
phalcon-1.0.10.33.dist-info/entry_points.txt
phalcon-1.0.10.33.dist-info/top_level.txt
phalcon-1.0.10.33.dist-info/RECORD
