Metadata-Version: 2.1
Name: phalcon
Version: 1.0.10.33
Summary: Command Line Interface for phalcon dev env
Home-page: UNKNOWN
Author: Wilson Mendoza
Author-email: mreyeswilson@gmail.com
License: UNKNOWN
Platform: UNKNOWN
Requires-Dist: certifi ==2023.7.22
Requires-Dist: cffi ==1.16.0
Requires-Dist: charset-normalizer ==3.3.2
Requires-Dist: click ==8.1.7
Requires-Dist: cryptography ==41.0.5
Requires-Dist: Deprecated ==1.2.14
Requires-Dist: docker ==6.1.3
Requires-Dist: gitdb ==4.0.11
Requires-Dist: GitPython ==3.1.40
Requires-Dist: idna ==3.4
Requires-Dist: inquirerpy ==0.3.4
Requires-Dist: packaging ==23.2
Requires-Dist: pfzy ==0.3.4
Requires-Dist: prompt-toolkit ==3.0.39
Requires-Dist: pycparser ==2.21
Requires-Dist: PyGithub ==2.1.1
Requires-Dist: Pygments ==2.16.1
Requires-Dist: PyJWT ==2.8.0
Requires-Dist: PyNaCl ==1.5.0
Requires-Dist: python-dateutil ==2.8.2
Requires-Dist: python-hosts ==1.0.4
Requires-Dist: regex ==2023.10.3
Requires-Dist: requests ==2.31.0
Requires-Dist: six ==1.16.0
Requires-Dist: smmap ==5.0.1
Requires-Dist: termcolor ==2.3.0
Requires-Dist: typing-extensions ==4.8.0
Requires-Dist: urllib3 ==2.0.7
Requires-Dist: wcwidth ==0.2.9
Requires-Dist: websocket-client ==1.6.4
Requires-Dist: wrapt ==1.15.0
